zhkj_plugins/__init__.py
zhkj_plugins/exceptions.py
zhkj_plugins/plugin_base.py
zhkj_plugins/plugin_caller.py
zhkj_plugins/plugin_util.py
zhkj_plugins/pyproject_parser.py
zhkj_plugins/remote_config.py
zhkj_plugins/rpc_service.py
zhkj_plugins/secret_util.py
zhkj_plugins/task_progress_manager.py
zhkj_plugins/utils.py
zhkj_plugins/plugin_manager/__init__.py
zhkj_plugins/plugin_manager/archive_handler.py
zhkj_plugins/plugin_manager/config_manager.py
zhkj_plugins/plugin_manager/download_manager.py
zhkj_plugins/plugin_manager/models.py
zhkj_plugins/plugin_manager/plugin_install_manager.py
zhkj_plugins/plugin_manager/plugin_loader.py
zhkj_plugins/plugin_manager/plugin_manager.py
zhkj_plugins/plugin_manager/plugin_package_manager.py
zhkj_plugins/plugin_manager/plugin_runtime_manager.py
zhkj_plugins/plugin_manager/plugin_update_manager.py
zhkj_plugins/plugin_manager/plugin_utils.py
zhkj_plugins/plugin_manager/port_manager.py
zhkj_plugins/plugin_manager/process_manager.py
zhkj_plugins/plugin_manager/process_output_monitor.py
zhkj_plugins/plugin_manager/progresses.py
zhkj_plugins/plugin_manager/version_manager.py
zhkj_plugins/plugin_manager/dependency_manager/__init__.py
zhkj_plugins/plugin_manager/dependency_manager/dependency_manager.py
zhkj_plugins/plugin_manager/dependency_manager/dependency_models.py
zhkj_plugins/plugin_manager/dependency_manager/dependency_resolver.py
zhkj_plugins/wrap/__init__.py
zhkj_plugins/wrap/_mutex_method.py
zhkj_plugins/wrap/_singleton.py
zhkj_plugins_parent-2.0.0.4.dist-info/METADATA
zhkj_plugins_parent-2.0.0.4.dist-info/WHEEL
zhkj_plugins_parent-2.0.0.4.dist-info/top_level.txt
zhkj_plugins_parent-2.0.0.4.dist-info/RECORD
