Metadata-Version: 2.4
Name: zhkj-plugins-parent
Version: 2.0.0.4
Summary: 插件管理
Author-email: yasin <l1y0l20@qq.com>
Requires-Python: >=3.9
Requires-Dist: aiohttp>=3.13.2
Requires-Dist: fickling>=0.1.4
Requires-Dist: psutil>=6.1.0
Requires-Dist: pycryptodome==3.21.0
Requires-Dist: pyyaml>=6.0.3
Requires-Dist: requests==2.32.3
Requires-Dist: toml>=0.10.2
